symcirc/__init__.py
symcirc/analysis.py
symcirc/component.py
symcirc/laplace.py
symcirc/parse.py
symcirc/pole_zero.py
symcirc/solvers.py
symcirc/utils.py
symcirc-0.2.1.dist-info/LICENSE
symcirc-0.2.1.dist-info/METADATA
symcirc-0.2.1.dist-info/WHEEL
symcirc-0.2.1.dist-info/top_level.txt
symcirc-0.2.1.dist-info/RECORD
