Metadata-Version: 2.1
Name: symcirc
Version: 0.2.1
Summary: A python package for symbolic electronic circuit analysis
Home-page: https://github.com/MatyasVasek/SymCirc
Author: Matyas Vasek
Author-email: matyas.vasek@gmail.com
License: MIT license
Project-URL: Bug Tracker, https://github.com/MatyasVasek/SymCirc/issues
Classifier: Programming Language :: Python :: 3
Classifier: License :: OSI Approved :: MIT License
Classifier: Operating System :: OS Independent
Requires-Python: >=3.6
License-File: LICENSE
Requires-Dist: sympy
